{"chunk_definitions":[{"row":45,"row_count":1,"visible":true,"expansion_state":0,"options":{"engine":"r","label":"unnamed-chunk-3"},"document_id":"FC75EDE3","chunk_id":"c4uusrf0ho4ky","chunk_label":"unnamed-chunk-1"},{"row":50,"row_count":1,"visible":true,"expansion_state":0,"options":{"engine":"r","label":"unnamed-chunk-4"},"document_id":"FC75EDE3","chunk_id":"c1qb8zcu6hppk","chunk_label":"unnamed-chunk-2"},{"row":55,"row_count":1,"visible":true,"expansion_state":0,"options":{"engine":"r","label":"unnamed-chunk-5"},"document_id":"FC75EDE3","chunk_id":"csnr2kht42lm1","chunk_label":"unnamed-chunk-3"},{"row":58,"row_count":1,"visible":true,"expansion_state":0,"options":{"engine":"r","label":"unnamed-chunk-6"},"document_id":"FC75EDE3","chunk_id":"cb822vwzew5tc","chunk_label":"unnamed-chunk-4"},{"row":63,"row_count":1,"visible":true,"expansion_state":0,"options":{"engine":"r","label":"unnamed-chunk-7"},"document_id":"FC75EDE3","chunk_id":"cgazei9n2zicx","chunk_label":"unnamed-chunk-5"},{"row":77,"row_count":1,"visible":true,"expansion_state":0,"options":{"engine":"r","label":"unnamed-chunk-8"},"document_id":"FC75EDE3","chunk_id":"c2ig245wtjp78","chunk_label":"unnamed-chunk-6"},{"row":101,"row_count":1,"visible":true,"expansion_state":0,"options":{"engine":"r","label":"unnamed-chunk-9"},"document_id":"FC75EDE3","chunk_id":"cg12rfvn5klmh","chunk_label":"unnamed-chunk-7"},{"row":111,"row_count":1,"visible":true,"expansion_state":0,"options":{"engine":"r","label":"unnamed-chunk-10"},"document_id":"FC75EDE3","chunk_id":"ccazvjrcjdpq4","chunk_label":"unnamed-chunk-8"},{"row":116,"row_count":1,"visible":true,"expansion_state":0,"options":{"engine":"r","label":"unnamed-chunk-11"},"document_id":"FC75EDE3","chunk_id":"cldzo5pah88ny","chunk_label":"unnamed-chunk-9"},{"row":121,"row_count":1,"visible":true,"expansion_state":0,"options":{"engine":"r","label":"unnamed-chunk-12"},"document_id":"FC75EDE3","chunk_id":"cj30kcrcp0yzf","chunk_label":"unnamed-chunk-10"},{"row":126,"row_count":1,"visible":true,"expansion_state":0,"options":{"engine":"r","label":"unnamed-chunk-1"},"document_id":"FC75EDE3","chunk_id":"c6qoh544d86hh","chunk_label":"unnamed-chunk-11"},{"row":131,"row_count":1,"visible":true,"expansion_state":0,"options":{"engine":"r","label":"unnamed-chunk-2"},"document_id":"FC75EDE3","chunk_id":"c05ovbkb1a6v0","chunk_label":"unnamed-chunk-12"},{"row":136,"row_count":1,"visible":true,"expansion_state":0,"options":{"engine":"r","label":"unnamed-chunk-3"},"document_id":"FC75EDE3","chunk_id":"czj5re3uf58k7","chunk_label":"unnamed-chunk-13"},{"row":141,"row_count":1,"visible":true,"expansion_state":0,"options":{"engine":"r","label":"unnamed-chunk-4"},"document_id":"FC75EDE3","chunk_id":"cwqa9sadori0q","chunk_label":"unnamed-chunk-14"},{"row":146,"row_count":1,"visible":true,"expansion_state":0,"options":{"engine":"r","label":"unnamed-chunk-5"},"document_id":"FC75EDE3","chunk_id":"c0huwm0y7vrh1","chunk_label":"unnamed-chunk-15"},{"row":151,"row_count":1,"visible":true,"expansion_state":0,"options":{"engine":"r","label":"unnamed-chunk-6"},"document_id":"FC75EDE3","chunk_id":"c6sbgp62tbg5s","chunk_label":"unnamed-chunk-16"},{"row":156,"row_count":1,"visible":true,"expansion_state":0,"options":{"engine":"r","label":"unnamed-chunk-7"},"document_id":"FC75EDE3","chunk_id":"cyc41o4vxxlm2","chunk_label":"unnamed-chunk-17"},{"row":163,"row_count":1,"visible":true,"expansion_state":0,"options":{"engine":"r","label":"unnamed-chunk-8"},"document_id":"FC75EDE3","chunk_id":"c987u8orv20cm","chunk_label":"unnamed-chunk-18"},{"row":168,"row_count":1,"visible":true,"expansion_state":0,"options":{"engine":"r","label":"unnamed-chunk-9"},"document_id":"FC75EDE3","chunk_id":"c040808sbyn0g","chunk_label":"unnamed-chunk-19"},{"row":173,"row_count":1,"visible":true,"expansion_state":0,"options":{"engine":"r","label":"unnamed-chunk-10"},"document_id":"FC75EDE3","chunk_id":"c9pr2rypd0hzj","chunk_label":"unnamed-chunk-20"},{"row":178,"row_count":1,"visible":true,"expansion_state":0,"options":{"engine":"r","label":"unnamed-chunk-11"},"document_id":"FC75EDE3","chunk_id":"c2e8ur5hsmjts","chunk_label":"unnamed-chunk-21"},{"row":183,"row_count":1,"visible":true,"expansion_state":0,"options":{"engine":"r","label":"unnamed-chunk-12"},"document_id":"FC75EDE3","chunk_id":"cqjypkxji28vk","chunk_label":"unnamed-chunk-22"},{"row":188,"row_count":1,"visible":true,"expansion_state":0,"options":{"engine":"r","label":"unnamed-chunk-13"},"document_id":"FC75EDE3","chunk_id":"c0vgpkuzt5ar6","chunk_label":"unnamed-chunk-23"},{"row":193,"row_count":1,"visible":true,"expansion_state":0,"options":{"engine":"r","label":"unnamed-chunk-14"},"document_id":"FC75EDE3","chunk_id":"caq0e3hkkh9fx","chunk_label":"unnamed-chunk-24"},{"row":198,"row_count":1,"visible":true,"expansion_state":0,"options":{"engine":"r","label":"unnamed-chunk-15"},"document_id":"FC75EDE3","chunk_id":"cgj5dsyez655a","chunk_label":"unnamed-chunk-25"},{"row":203,"row_count":1,"visible":true,"expansion_state":0,"options":{"engine":"r","label":"unnamed-chunk-16"},"document_id":"FC75EDE3","chunk_id":"cwagv1l8d9rvm","chunk_label":"unnamed-chunk-26"},{"row":208,"row_count":1,"visible":true,"expansion_state":0,"options":{"engine":"r","label":"unnamed-chunk-17"},"document_id":"FC75EDE3","chunk_id":"cc0a441gb4rcy","chunk_label":"unnamed-chunk-27"},{"row":213,"row_count":1,"visible":true,"expansion_state":0,"options":{"engine":"r","label":"unnamed-chunk-18"},"document_id":"FC75EDE3","chunk_id":"cwxzw2scq9165","chunk_label":"unnamed-chunk-28"},{"row":218,"row_count":1,"visible":true,"expansion_state":0,"options":{"engine":"r","label":"unnamed-chunk-19"},"document_id":"FC75EDE3","chunk_id":"cb3jqr0tos5mu","chunk_label":"unnamed-chunk-29"},{"row":231,"row_count":1,"visible":true,"expansion_state":0,"options":{"engine":"r","label":"unnamed-chunk-20"},"document_id":"FC75EDE3","chunk_id":"co8696472o6ok","chunk_label":"unnamed-chunk-30"},{"row":243,"row_count":1,"visible":true,"expansion_state":0,"options":{"engine":"r","label":"unnamed-chunk-21"},"document_id":"FC75EDE3","chunk_id":"czb7bs2qf90df","chunk_label":"unnamed-chunk-31"},{"row":256,"row_count":1,"visible":true,"expansion_state":0,"options":{"engine":"r","label":"unnamed-chunk-22"},"document_id":"FC75EDE3","chunk_id":"cfigg9brtvax9","chunk_label":"unnamed-chunk-32"},{"row":263,"row_count":1,"visible":true,"expansion_state":0,"options":{"engine":"r","label":"unnamed-chunk-23"},"document_id":"FC75EDE3","chunk_id":"cw3llrwkoot2g","chunk_label":"unnamed-chunk-33"},{"row":276,"row_count":1,"visible":true,"expansion_state":0,"options":{"engine":"r","label":"unnamed-chunk-24"},"document_id":"FC75EDE3","chunk_id":"cfcklj1tkk20z","chunk_label":"unnamed-chunk-34"},{"row":281,"row_count":1,"visible":true,"expansion_state":0,"options":{"engine":"r","label":"unnamed-chunk-25"},"document_id":"FC75EDE3","chunk_id":"chstnnabe7qv4","chunk_label":"unnamed-chunk-35"},{"row":288,"row_count":1,"visible":true,"expansion_state":0,"options":{"engine":"r","label":"unnamed-chunk-26"},"document_id":"FC75EDE3","chunk_id":"cn7a52tgnytma","chunk_label":"unnamed-chunk-36"},{"row":297,"row_count":1,"visible":true,"expansion_state":0,"options":{"engine":"r","label":"unnamed-chunk-27"},"document_id":"FC75EDE3","chunk_id":"c4izb8zaoo1vo","chunk_label":"unnamed-chunk-37"},{"row":304,"row_count":1,"visible":true,"expansion_state":0,"options":{"engine":"r","label":"unnamed-chunk-28"},"document_id":"FC75EDE3","chunk_id":"c8j6naoyy3h8n","chunk_label":"unnamed-chunk-38"},{"row":317,"row_count":1,"visible":true,"expansion_state":0,"options":{"engine":"r","label":"unnamed-chunk-29"},"document_id":"FC75EDE3","chunk_id":"c5ckw7qcerfsw","chunk_label":"unnamed-chunk-39"},{"row":331,"row_count":1,"visible":true,"expansion_state":0,"options":{"engine":"r","label":"unnamed-chunk-30"},"document_id":"FC75EDE3","chunk_id":"c2d8ag0ufy1zi","chunk_label":"unnamed-chunk-40"},{"row":339,"row_count":1,"visible":true,"expansion_state":0,"options":{"engine":"r","label":"unnamed-chunk-31"},"document_id":"FC75EDE3","chunk_id":"cfw187ysymmvm","chunk_label":"unnamed-chunk-41"},{"row":347,"row_count":1,"visible":true,"expansion_state":0,"options":{"engine":"r","label":"unnamed-chunk-32"},"document_id":"FC75EDE3","chunk_id":"c1a3jpf8rzh5v","chunk_label":"unnamed-chunk-42"},{"row":353,"row_count":1,"visible":true,"expansion_state":0,"options":{"engine":"r","label":"unnamed-chunk-33"},"document_id":"FC75EDE3","chunk_id":"ccllfnoaqn0ry","chunk_label":"unnamed-chunk-43"},{"row":361,"row_count":1,"visible":true,"expansion_state":0,"options":{"engine":"r","label":"unnamed-chunk-34"},"document_id":"FC75EDE3","chunk_id":"c4j2xi7kqgfzw","chunk_label":"unnamed-chunk-44"},{"row":372,"row_count":1,"visible":true,"expansion_state":0,"options":{"engine":"r","label":"unnamed-chunk-35"},"document_id":"FC75EDE3","chunk_id":"cexugxr8pyim7","chunk_label":"unnamed-chunk-45"},{"row":383,"row_count":1,"visible":true,"expansion_state":0,"options":{"engine":"r","label":"unnamed-chunk-36"},"document_id":"FC75EDE3","chunk_id":"ct9zofo17sw5a","chunk_label":"unnamed-chunk-46"},{"row":390,"row_count":1,"visible":true,"expansion_state":0,"options":{"engine":"r","label":"unnamed-chunk-37"},"document_id":"FC75EDE3","chunk_id":"c1z2z2omxjl7d","chunk_label":"unnamed-chunk-47"},{"row":401,"row_count":1,"visible":true,"expansion_state":0,"options":{"engine":"r","label":"unnamed-chunk-38"},"document_id":"FC75EDE3","chunk_id":"c0hken0u8n9tv","chunk_label":"unnamed-chunk-48"},{"row":407,"row_count":1,"visible":true,"expansion_state":0,"options":{"engine":"r","label":"unnamed-chunk-39"},"document_id":"FC75EDE3","chunk_id":"c2q22xogzs6jf","chunk_label":"unnamed-chunk-49"},{"row":415,"row_count":1,"visible":true,"expansion_state":0,"options":{"engine":"r","label":"unnamed-chunk-40"},"document_id":"FC75EDE3","chunk_id":"cd0c8e65pbrkk","chunk_label":"unnamed-chunk-50"},{"row":423,"row_count":1,"visible":true,"expansion_state":0,"options":{"engine":"r","label":"unnamed-chunk-41"},"document_id":"FC75EDE3","chunk_id":"cwfs89bv57iwv","chunk_label":"unnamed-chunk-51"},{"row":431,"row_count":1,"visible":true,"expansion_state":0,"options":{"engine":"r","label":"unnamed-chunk-42"},"document_id":"FC75EDE3","chunk_id":"c9yx2cr4t0k8n","chunk_label":"unnamed-chunk-52"},{"row":447,"row_count":1,"visible":true,"expansion_state":0,"options":{"engine":"r","label":"unnamed-chunk-43"},"document_id":"FC75EDE3","chunk_id":"ctd0rl9sw8hck","chunk_label":"unnamed-chunk-53"},{"row":455,"row_count":1,"visible":true,"expansion_state":0,"options":{"engine":"r","label":"unnamed-chunk-44"},"document_id":"FC75EDE3","chunk_id":"c51uzow7ry9hw","chunk_label":"unnamed-chunk-54"},{"row":461,"row_count":1,"visible":true,"expansion_state":0,"options":{"engine":"r","label":"unnamed-chunk-45"},"document_id":"FC75EDE3","chunk_id":"cqc2pibmcujvj","chunk_label":"unnamed-chunk-55"},{"row":469,"row_count":1,"visible":true,"expansion_state":0,"options":{"engine":"r","label":"unnamed-chunk-46"},"document_id":"FC75EDE3","chunk_id":"c0jpvugd2tv12","chunk_label":"unnamed-chunk-56"},{"row":483,"row_count":1,"visible":true,"expansion_state":0,"options":{"engine":"r","label":"unnamed-chunk-47"},"document_id":"FC75EDE3","chunk_id":"ci2sjmq4n9b6h","chunk_label":"unnamed-chunk-57"},{"row":492,"row_count":1,"visible":true,"expansion_state":0,"options":{"engine":"r","label":"unnamed-chunk-48"},"document_id":"FC75EDE3","chunk_id":"cxl2mgxae9snn","chunk_label":"unnamed-chunk-58"},{"row":500,"row_count":1,"visible":true,"expansion_state":0,"options":{"engine":"r","label":"unnamed-chunk-49"},"document_id":"FC75EDE3","chunk_id":"cho7o25b77hoo","chunk_label":"unnamed-chunk-59"}],"doc_write_time":1610908401}